cloudflare_bypass/__init__.py
cloudflare_bypass/auto.py
cloudflare_bypass/base_detector.py
cloudflare_bypass/cloudflare_detector.py
cloudflare_bypass/images/cf_logo.png
cloudflare_bypass/images/cf_logo_dark.png
cloudflare_bypass/images/cf_popup.png
cloudflare_bypass/images/cf_popup_dark.png
tests/__init__.py
tests/test_auto.py
cloudflare_bypass-0.1.1.dist-info/LICENSE
cloudflare_bypass-0.1.1.dist-info/METADATA
cloudflare_bypass-0.1.1.dist-info/WHEEL
cloudflare_bypass-0.1.1.dist-info/top_level.txt
cloudflare_bypass-0.1.1.dist-info/RECORD
