Metadata-Version: 2.1
Name: cloudflare-bypass
Version: 0.1.1
Summary: A tool for bypassing Cloudflare CAPTCHA
Home-page: https://github.com/tamnguyenvan/cloudflare-bypass
Author: Tam Nguyen
Author-email: tamnvhustcc@gmail.com
Project-URL: Documentation, https://tamnguyenvan.github.io/cloudflare-bypass
Project-URL: Source, https://github.com/tamnguyenvan/cloudflare-bypass
Keywords: cloudflare captcha bypass
Classifier: Development Status :: 5 - Production/Stable
Classifier: Intended Audience :: Developers
Classifier: License :: OSI Approved :: MIT License
Classifier: Programming Language :: Python :: 3
Classifier: Programming Language :: Python :: 3.6
Classifier: Programming Language :: Python :: 3.7
Classifier: Programming Language :: Python :: 3.8
Classifier: Programming Language :: Python :: 3.9
Classifier: Programming Language :: Python :: 3.10
Classifier: Programming Language :: Python :: 3.11
Classifier: Programming Language :: Python :: 3.12
Classifier: Topic :: Software Development :: Libraries
Classifier: Topic :: Software Development :: Libraries :: Python Modules
License-File: LICENSE
Requires-Dist: Pillow
Requires-Dist: numpy
Requires-Dist: opencv-python
Requires-Dist: pyautogui
